hacker_news_to_sqlite/__init__.py
hacker_news_to_sqlite/cli.py
hacker_news_to_sqlite-0.4.dist-info/LICENSE
hacker_news_to_sqlite-0.4.dist-info/METADATA
hacker_news_to_sqlite-0.4.dist-info/WHEEL
hacker_news_to_sqlite-0.4.dist-info/entry_points.txt
hacker_news_to_sqlite-0.4.dist-info/top_level.txt
hacker_news_to_sqlite-0.4.dist-info/RECORD
