Metadata-Version: 2.1
Name: hacker-news-to-sqlite
Version: 0.4
Summary: Create a SQLite database containing data pulled from Hacker News
Home-page: https://github.com/dogsheep/hacker-news-to-sqlite
Author: Simon Willison
License: Apache License, Version 2.0
Platform: UNKNOWN
Requires-Dist: sqlite-utils
Requires-Dist: click
Requires-Dist: requests
Requires-Dist: tqdm
Provides-Extra: test
Requires-Dist: pytest ; extra == 'test'
Requires-Dist: requests-mock ; extra == 'test'
